Workbook

Sheet Cover
B3: Amazon
C7: Table of Content
C10: Output | K10: What this model has?
C14: Inputs
C18: DCF Evaluation
C22: Model

Sheet Output
B4: DCF EVALUATION OF AMAZON
C7: Table of Content | O7: Notes :-
D13: Inputs
O14: A. This model works on certain key Assumptions and Scenarios
D17: DCF Evaluation | O17: B. Forcast FCFF- are only for 5 years
O20: C. There are several model checks
D22: Model
O23: D. There are certain model limitations

Sheet Input
A1: DRIVERS
B4: DRIVER SWITCH | C4: 1
C6: CASES
C9: SALES GROWTH | G9: {=_xlfn.IFS($C$4=1,G10,$C$4=2,G11,$C$4=3,G12,$C$4=4,G13)} -> 0.025 | H9: {=_xlfn.IFS($C$4=1,H10,$C$4=2,H11,$C$4=3,H12,$C$4=4,H13)} -> 0.03 | I9: {=_xlfn.IFS($C$4=1,I10,$C$4=2,I11,$C$4=3,I12,$C$4=4,I13)} -> 0.0275 | J9: {=_xlfn.IFS($C$4=1,J10,$C$4=2,J11,$C$4=3,J12,$C$4=4,J13)} -> 0.0275 | K9: {=_xlfn.IFS($C$4=1,K10,$C$4=2,K11,$C$4=3,K12,$C$4=4,K13)} -> 0.028333333
D10: BEST CASE | G10: 0.025 | H10: 0.03 | I10: =AVERAGE(F10:H10) -> 0.0275 | J10: =AVERAGE(G10:I10) -> 0.0275 | K10: =AVERAGE(H10:J10) -> 0.028333333
D11: BASE CASE | G11: 0.02 | H11: 0.025 | I11: =AVERAGE(F11:H11) -> 0.0225 | J11: =AVERAGE(G11:I11) -> 0.0225 | K11: =AVERAGE(H11:J11) -> 0.023333333
D12: WORST CASE | G12: 0.01 | H12: 0.01 | I12: =AVERAGE(F12:H12) -> 0.01 | J12: =AVERAGE(G12:I12) -> 0.01 | K12: =AVERAGE(H12:J12) -> 0.01
D13: OFF | G13: 0 | H13: 0 | I13: =AVERAGE(F13:H13) -> 0 | J13: =AVERAGE(G13:I13) -> 0 | K13: =AVERAGE(H13:J13) -> 0
C17: PRICING INCREASE | G17: {=_xlfn.IFS($C$4=1,G18,$C$4=2,G19,$C$4=3,G20,$C$4=4,G21)} -> 0.032 | H17: {=_xlfn.IFS($C$4=1,H18,$C$4=2,H19,$C$4=3,H20,$C$4=4,H21)} -> 0.035 | I17: {=_xlfn.IFS($C$4=1,I18,$C$4=2,I19,$C$4=3,I20,$C$4=4,I21)} -> 0.0335 | J17: {=_xlfn.IFS($C$4=1,J18,$C$4=2,J19,$C$4=3,J20,$C$4=4,J21)} -> 0.0335 | K17: {=_xlfn.IFS($C$4=1,K18,$C$4=2,K19,$C$4=3,K20,$C$4=4,K21)} -> 0.034
D18: BEST CASE | G18: 0.032 | H18: 0.035 | I18: =AVERAGE(F18:H18) -> 0.0335 | J18: =AVERAGE(G18:I18) -> 0.0335 | K18: =AVERAGE(H18:J18) -> 0.034
D19: BASE CASE | G19: 0.02 | H19: 0.02 | I19: =AVERAGE(F19:H19) -> 0.02 | J19: =AVERAGE(G19:I19) -> 0.02 | K19: =AVERAGE(H19:J19) -> 0.02
D20: WORST CASE | G20: 0.01 | H20: 0.01 | I20: =AVERAGE(F20:H20) -> 0.01 | J20: =AVERAGE(G20:I20) -> 0.01 | K20: =AVERAGE(H20:J20) -> 0.01
D21: OFF | G21: 0 | H21: 0 | I21: =AVERAGE(F21:H21) -> 0 | J21: =AVERAGE(G21:I21) -> 0 | K21: =AVERAGE(H21:J21) -> 0
C25: CAPITAL EXPENDITURE | G25: {=_xlfn.IFS($C$4=1,G26,$C$4=2,G27,$C$4=3,G28,$C$4=4,G29)} -> 95000 | H25: {=_xlfn.IFS($C$4=1,H26,$C$4=2,H27,$C$4=3,H28,$C$4=4,H29)} -> 97500 | I25: {=_xlfn.IFS($C$4=1,I26,$C$4=2,I27,$C$4=3,I28,$C$4=4,I29)} -> 96250 | J25: {=_xlfn.IFS($C$4=1,J26,$C$4=2,J27,$C$4=3,J28,$C$4=4,J29)} -> 96250 | K25: {=_xlfn.IFS($C$4=1,K26,$C$4=2,K27,$C$4=3,K28,$C$4=4,K29)} -> 96666.667
D26: BEST CASE | G26: 95000 | H26: 97500 | I26: =AVERAGE(F26:H26) -> 96250 | J26: =AVERAGE(G26:I26) -> 96250 | K26: =AVERAGE(H26:J26) -> 96666.667
D27: BASE CASE | G27: 74500 | H27: 75000 | I27: =AVERAGE(F27:H27) -> 74750 | J27: =AVERAGE(G27:I27) -> 74750 | K27: =AVERAGE(H27:J27) -> 74833.333
D28: WORST CASE | G28: 22000 | H28: 25000 | I28: =AVERAGE(F28:H28) -> 23500 | J28: =AVERAGE(G28:I28) -> 23500 | K28: =AVERAGE(H28:J28) -> 24000
D29: OFF | G29: 0 | H29: 0 | I29: =AVERAGE(F29:H29) -> 0 | J29: =AVERAGE(G29:I29) -> 0 | K29: =AVERAGE(H29:J29) -> 0
C45: All the values are in MILLIONS
D51: Working capital
D53: Account Recievable | E53: (Days) | G53: 32 | H53: 35 | I53: =AVERAGE(F53:H53) -> 33.5 | J53: =AVERAGE(G53:I53) -> 33.5 | K53: =AVERAGE(H53:J53) -> 34
D54: Inventories | E54: (Days) | G54: 30 | H54: 35 | I54: =AVERAGE(F54:H54) -> 32.5 | J54: =AVERAGE(G54:I54) -> 32.5 | K54: =AVERAGE(H54:J54) -> 33.333333
D55: Accounts Payable | E55: (Days) | G55: 100 | H55: 125 | I55: =AVERAGE(F55:H55) -> 112.5 | J55: =AVERAGE(G55:I55) -> 112.5 | K55: =AVERAGE(H55:J55) -> 116.66667
D59: Other Annual Inputs
D63: INFLATION RATE | G63: {=_xlfn.IFS($C$4=1,G64,$C$4=2,G64,$C$4=3,G64,$C$4=4,G64)} -> 0.02 | H63: {=_xlfn.IFS($C$4=1,H64,$C$4=2,H64,$C$4=3,H64,$C$4=4,H64)} -> 0.02 | I63: =AVERAGE(F63:H63) -> 0.02 | J63: =AVERAGE(G63:I63) -> 0.02 | K63: =AVERAGE(H63:J63) -> 0.02
G64: 0.02 | H64: 0.02 | I64: 0.025 | J64: =AVERAGE(G64:I64) -> 0.021666667 | K64: =AVERAGE(H64:J64) -> 0.022222222
D66: Common Equity | E66: (Assume) | G66: -2500 | H66: -2500 | I66: =AVERAGE(F66:H66) -> -2500 | J66: =AVERAGE(G66:I66) -> -2500 | K66: =AVERAGE(H66:J66) -> -2500
D67: Term Debts | E67: (Assume) | G67: -400 | H67: -450 | I67: =AVERAGE(F67:H67) -> -425 | J67: =AVERAGE(G67:I67) -> -425 | K67: =AVERAGE(H67:J67) -> -433.33333
D69: TERMINAL GROWTH | G69: 0.025 | H69: 0.025
D70: Depreciation
D73: First year accounting depreciation | G73: 0.5
D74: Useful life (Existing assets) | E74: Years | G74: 11
D75: Useful life (New assets) | E75: Years | G75: 20
D77: Taxes
D80: Tax Rate | G80: 0.2
D81: First Year Depreciation | G81: 0.5
D82: Blended Taxes | G82: 0.25
D88: Interest Rates
D91: Cash | F91: 0.05
D92: Credit line | F92: 0.1
D93: Long term Debt | F93: 0.15
D94: Pay out Ratio | F94: 0.1

Sheet DCF Evaluation
B2: DCF Evaluation
B6: FCFF | O6: WACC | AB6: Calculations for Wacc
B8: All the values are in Millions | O8: All the values are in Millions | AB8: Return on Equity | AG8: Return on Debt
Y9: 2025 | Z9: 2030
D10: 2025 | F10: 2026 | H10: 2027 | J10: 2028 | L10: 2029 | N10: 2030
B11: REVENUE | D11: =Model!J9 -> 716924 | F11: =Model!K9 -> 734847.1 | H11: =Model!L9 -> 756892.51 | J11: =Model!M9 -> 777707.06 | L11: =Model!N9 -> 799094 | N11: =Model!O9 -> 821735 | O11: VARIABLE NAME | R11: ABREVATION | T11: 2025 | V11: 2030F | W11: Equity | Y11: =Model!J128 -> 411065 | Z11: =Model!O128 -> 845899.3 | AB11: Cost of Equity | AG11: Cost of Debt
AE12: 2025 | AF12: 2030 | AJ12: 2025 | AK12: 2030
O13: RETURN ON EQUITY | R13: RE | T13: =AE19 -> 0.099 | V13: =AF19 -> 0.1025 | W13: Debt | Y13: =Model!J120 -> 65648 | Z13: =Model!O120 -> 63514.667 | AB13: Risk Free Rate | AE13: 0.05 | AF13: 0.05 | AG13: Interest Expense | AJ13: =Y17 -> 2274 | AK13: =Z17 -> 2510.6797
B15: EBIT | D15: =Model!J20 -> 79975 | F15: =Model!K20 -> 85159.12 | H15: =Model!L20 -> 94210.773 | J15: =Model!M20 -> 101771.68 | L15: =Model!N20 -> 109639.92 | N15: =Model!O20 -> 118491.83 | O15: RETURN ON DEBT | R15: RD | T15: =AJ25 -> 0.030763247 | V15: =AK25 -> 0.031515798 | W15: Tax Rate | Y15: =Input!G80 -> 0.2 | Z15: =Y15 -> 0.2 | AB15: Beta | AE15: 1.4 | AF15: 1.5 | AG15: Total Debt | AJ15: =AVERAGE(Model!I120:J120) -> 59135.5 | AK15: =AVERAGE(Model!N120:O120) -> 63731.333
O17: TAX RATE | R17: T | T17: =Y15 -> 0.2 | V17: =Z15 -> 0.2 | W17: Interest Expense | Y17: =-Model!J27 -> 2274 | Z17: =-Model!O27 -> 2510.6797 | AB17: Equity Risk Premium | AE17: 0.035 | AF17: 0.035 | AG17: Cost of Debt | AJ17: =AJ13/AJ15 -> 0.038454059 | AK17: =AK13/AK15 -> 0.039394747
B18: TAX Rate | D18: =Y15 -> 0.2 | F18: =$Z$15 -> 0.2 | H18: =$Z$15 -> 0.2 | J18: =$Z$15 -> 0.2 | L18: =$Z$15 -> 0.2 | N18: =$Z$15 -> 0.2
O19: VALUE OF EQUITY | R19: E | T19: =Y11 -> 411065 | V19: =Z11 -> 845899.3 | W19: Income Tax Expense | Y19: =-Model!J32 -> 19087 | Z19: =-Model!O32 -> 21073.59 | AB19: Cost of Equity | AE19: =AE13+(AE15*AE17) -> 0.099 | AF19: =AF13+(AF15*AF17) -> 0.1025 | AG19: Income Tax Expense | AJ19: =Y19 -> 19087 | AK19: =Z19 -> 21073.59
B21: NOPAT | D21: =D15*(1-D18) -> 63980 | F21: =F15*(1-F18) -> 68127.296 | H21: =H15*(1-H18) -> 75368.619 | J21: =J15*(1-J18) -> 81417.346 | L21: =L15*(1-L18) -> 87711.935 | N21: =N15*(1-N18) -> 94793.467 | O21: VALUE OF DEBT | R21: D | T21: =Y13 -> 65648 | V21: =Z13 -> 63514.667 | W21: EBT | Y21: =Model!J31 -> 97311 | Z21: =Model!O31 -> 137632.18 | AG21: EBT | AJ21: =Y21 -> 97311 | AK21: =Z21 -> 137632.18
O23: VALUE OF DEBT+ EQUITY | R23: V | T23: =T19+T21 -> 476713 | V23: =V19+V21 -> 909413.97 | W23: Effective Tax Rate | Y23: =Input!G80 -> 0.2 | Z23: =Y23 -> 0.2 | AG23: Effective Tax Rate | AJ23: =Y23 -> 0.2 | AK23: =Z23 -> 0.2
B24: D&A | D24: =Model!J22 -> 65756 | F24: =Model!K22 -> 32854.718 | H24: =Model!L22 -> 32979.718 | J24: =Model!M22 -> 33098.468 | L24: =Model!N22 -> 33218.781 | N24: =Model!O22 -> 33340.135
W25: CASH | Y25: =Model!J93 -> 86810 | Z25: =Model!O93 -> 200778.37 | AG25: Cost of debt after tax | AJ25: =AJ17*(1-AJ23) -> 0.030763247 | AK25: =AK17*(1-AK23) -> 0.031515798
O26: EQUITY % VALUE | R26: EV | T26: =T19/T23 -> 0.86229031 | V26: =V19/V23 -> 0.93015869
B27: CAPEX | D27: =Model!J60 -> -128320 | F27: =Model!K60 -> -95000 | H27: =Model!L60 -> -97500 | J27: =Model!M60 -> -96250 | L27: =Model!N60 -> -96250 | N27: =Model!O60 -> -96666.667 | W27: DISCOUNT PERIOD | Y27: 0 | Z27: 6
O28: DEBT % VALUE | R28: DV | T28: =T21/T23 -> 0.13770969 | V28: =V21/V23 -> 0.069841314
B30: CHANGE IN WC | D30: =Model!J204 -> -11157 | F30: =Model!K204 -> 10559.514 | H30: =Model!L204 -> -13559.153 | J30: =Model!M204 -> 7333.6403 | L30: =Model!N204 -> 304.91947 | N30: =Model!O204 -> -2081.1753
O31: WACC | R31: WACC | T31: =(T26*T13)+(T28*T15) -> 0.089603138 | V31: =(V26*V13)+(V28*V15) -> 0.09754237
B33: FCFF | D33: =D21+D24+D27-D30 -> 12573 | F33: =F21+F24+F27-F30 -> -4577.4998 | H33: =H21+H24+H27-H30 -> 24407.49 | J33: =J21+J24+J27-J30 -> 10932.174 | L33: =L21+L24+L27-L30 -> 24375.797 | N33: =N21+N24+N27-N30 -> 33548.111
B35: Discounted Period | D35: 0 | F35: 1 | H35: =F35+1 -> 2 | J35: =H35+1 -> 3 | L35: =J35+1 -> 4 | N35: =L35+1 -> 5
B37: Present FCFF | D37: =D33/(1+T31)^D35 -> 12573 | F37: =F33/(1+$V$31)^F35 -> -4170.6816 | H37: =H33/(1+$V$31)^H35 -> 20261.917 | J37: =J33/(1+$V$31)^J35 -> 8268.8031 | L37: =L33/(1+$V$31)^L35 -> 16798.621 | N37: =N33/(1+$V$31)^N35 -> 21065.006
B47: TERMINAL VALUE | I47: ENTERPRISE VALUE
P48: VALUATION SUMMARY
F49: 2025 | G49: 2030 | K49: 2025 | L49: 2030
Q50: ALL THE VALUES ARE IN MILLIONS | U50: 2026
C51: TERMINAL GROWTH RATE | F51: =Input!G69 -> 0.025 | G51: =Input!H69 -> 0.025 | I51: EQUITY | K51: =Y11 -> 411065 | L51: =Z11 -> 845899.3
C53: WACC | F53: =T31 -> 0.089603138 | G53: =$T$31 -> 0.089603138 | I53: DEBT | K53: =Y13 -> 65648 | L53: =Z13 -> 63514.667
Q54: PV OF FORCAST FCFF | U54: =SUM(F37:N37) -> 62223.666
C55: FCFF | F55: =D33 -> 12573 | G55: =N33 -> 33548.111 | I55: CASH | K55: =Y25 -> 86810 | L55: =Z25 -> 200778.37
Q56: 2030 FCFF (undiscounted) | U56: =N33 -> 33548.111
I57: EV | K57: =K51+K53-K55/F58 -> 476712.56 | L57: =L51+L53-L55/G58 -> 909413.59
C58: TERMINAL VALUE | F58: =F55*(1+F51)/(F53-F51) -> 199484.51 | G58: =G55*(1+G51)/(G53-G51) -> 532277.76 | Q58: TERMINAL VALUE END OF 2030 | U58: =G58 -> 532277.76
Q60: PV TERMINAL VALUE | U60: =U58/(1+V31)^N35 -> 334219.55
Q62: ENTERPRISE VALUE | U62: =U54+U60 -> 396443.22

Sheet Model
A1: INCOME STATEMENT
C2: All the values are in MILLIONS
F4: 2021 | G4: 2022 | H4: 2023 | I4: 2024 | J4: 2025 | K4: 2026F | L4: 2027F | M4: 2028F | N4: 2029F | O4: 2030F
B5: Revenue
B6: Inflation | K6: =Input!G63 -> 0.02 | L6: =Input!H63 -> 0.02 | M6: =Input!I63 -> 0.02 | N6: =Input!J63 -> 0.02 | O6: =Input!K63 -> 0.02
B7: %Change in COGS | K7: =K10/J10-1 -> 0.02 | L7: =L10/K10-1 -> 0.02
B9: REVENUE | F9: 469822 | G9: 513983 | H9: 574785 | I9: 637959 | J9: 716924 | K9: =K160 -> 734847.1 | L9: =L160 -> 756892.51 | M9: =M160 -> 777707.06 | N9: =N160 -> 799094 | O9: =O160 -> 821735
C10: COGS | F10: -272344 | G10: -288831 | H10: -304739 | I10: -326288 | J10: -356414 | K10: =J10*(1+K6) -> -363542.28 | L10: =K10*(1+L6) -> -370813.13 | M10: =L10*(1+M6) -> -378229.39 | N10: =M10*(1+N6) -> -385793.98 | O10: =N10*(1+O6) -> -393509.86
B12: GROSS PROFIT | F12: =SUM(F9:F11) -> 197478 | G12: =SUM(G9:G11) -> 225152 | H12: =SUM(H9:H11) -> 270046 | I12: =SUM(I9:I11) -> 311671 | J12: =SUM(J9:J11) -> 360510 | K12: =SUM(K9:K11) -> 371304.82 | L12: =SUM(L9:L11) -> 386079.39 | M12: =SUM(M9:M11) -> 399477.67 | ... O12: =SUM(O9:O11) -> 428225.14
C14: FULFILMENT | F14: -75111 | G14: -84299 | H14: -90619 | I14: -98505 | J14: -109074 | K14: =J14*(1+$K$6) -> -111255.48 | L14: =K14*(1+$L$6) -> -113480.59 | M14: =L14*(1+$L$6) -> -115750.2 | N14: =M14*(1+$L$6) -> -118065.21 | O14: =N14*(1+$L$6) -> -120426.51
C15: TECHNOLOGY | F15: -56052 | G15: -73213 | H15: -85622 | I15: -88544 | J15: -108521 | K15: =J15*(1+$K$6) -> -110691.42 | L15: =K15*(1+$L$6) -> -112905.25 | M15: =L15*(1+$L$6) -> -115163.35 | N15: =M15*(1+$L$6) -> -117466.62 | O15: =N15*(1+$L$6) -> -119815.95
C16: SALES AND MARKETING | F16: -32551 | G16: -42238 | H16: -44370 | I16: -43907 | J16: -47129 | K16: =J16*(1+$K$6) -> -48071.58 | L16: =K16*(1+$L$6) -> -49033.012 | M16: =L16*(1+$L$6) -> -50013.672 | N16: =M16*(1+$L$6) -> -51013.945 | O16: =N16*(1+$L$6) -> -52034.224
C17: ADMIN/SG&A | F17: -8823 | G17: -11891 | H17: -11816 | I17: -11359 | J17: -11172 | K17: =J17*(1+$K$6) -> -11395.44 | L17: =K17*(1+$L$6) -> -11623.349 | M17: =L17*(1+$L$6) -> -11855.816 | N17: =M17*(1+$L$6) -> -12092.932 | O17: =N17*(1+$L$6) -> -12334.791
C18: OTHER OPERATING EXPENSE | F18: -62 | G18: -1263 | H18: -767 | I18: -763 | J18: -4639 | K18: =J18*(1+$K$6) -> -4731.78 | L18: =K18*(1+$L$6) -> -4826.4156 | M18: =L18*(1+$L$6) -> -4922.9439 | N18: =M18*(1+$L$6) -> -5021.4028 | O18: =N18*(1+$L$6) -> -5121.8308
B20: EBIT | F20: =SUM(F12:F19) -> 24879 | G20: =SUM(G12:G19) -> 12248 | H20: =SUM(H12:H19) -> 36852 | I20: =SUM(I12:I19) -> 68593 | J20: =SUM(J12:J19) -> 79975 | K20: =SUM(K12:K19) -> 85159.12 | L20: =SUM(L12:L19) -> 94210.773 | M20: =SUM(M12:M19) -> 101771.68 | ... O20: =SUM(O12:O19) -> 118491.83
C22: DEPRECIATION & AMORTIZATION | F22: 34433 | G22: 41921 | H22: 48663 | I22: 52795 | J22: 65756 | K22: =K51 -> 32854.718 | L22: =L51 -> 32979.718 | M22: =M51 -> 33098.468 | N22: =N51 -> 33218.781 | O22: =O51 -> 33340.135
B23: EBITDA | F23: =SUM(F20:F22) -> 59312 | G23: =SUM(G20:G22) -> 54169 | H23: =SUM(H20:H22) -> 85515 | I23: =SUM(I20:I22) -> 121388 | J23: =SUM(J20:J22) -> 145731 | K23: =SUM(K20:K22) -> 118013.84 | L23: =SUM(L20:L22) -> 127190.49 | M23: =SUM(M20:M22) -> 134870.15 | ... O23: =SUM(O20:O22) -> 151831.97
C26: FINANCE INCOME | F26: 448 | G26: 989 | H26: 2949 | I26: 4677 | J26: 4381 | K26: =J26*(1+$K$6) -> 4468.62 | L26: =K26*(1+$K$6) -> 4557.9924 | M26: =L26*(1+$K$6) -> 4649.1522 | N26: =M26*(1+$K$6) -> 4742.1353 | O26: =N26*(1+$K$6) -> 4836.978
C27: FINANCE COSTS | F27: -1809 | G27: -2367 | H27: -3182 | I27: -2406 | J27: -2274 | K27: =J27*(1+$K$6) -> -2319.48 | L27: =K27*(1+$K$6) -> -2365.8696 | M27: =L27*(1+$K$6) -> -2413.187 | N27: =M27*(1+$K$6) -> -2461.4507 | O27: =N27*(1+$K$6) -> -2510.6797
C28: SHAREOF JVS AND ASSOCIATES | F28: 14633 | G28: -16806 | H28: 938 | I28: -2250 | J28: 15229 | K28: =J28*(1+$K$6) -> 15533.58 | L28: =K28*(1+$K$6) -> 15844.252 | M28: =L28*(1+$K$6) -> 16161.137 | N28: =M28*(1+$K$6) -> 16484.359 | O28: =N28*(1+$K$6) -> 16814.047
B31: EBT | F31: =SUM(F20,F26:F28) -> 38151 | G31: =SUM(G20,G26:G28) -> -5936 | H31: =SUM(H20,H26:H28) -> 37557 | I31: =SUM(I20,I26:I28) -> 68614 | J31: =SUM(J20,J26:J28) -> 97311 | K31: =SUM(K20,K26:K30) -> 102841.84 | L31: =SUM(L20,L26:L30) -> 112247.15 | M31: =SUM(M20,M26:M30) -> 120168.78 | N31: =SUM(N20,N26:N30) -> 128404.96 | O31: =SUM(O20,O26:O30) -> 137632.18
C32: INCOME TAX EXPENSE | F32: -4791 | G32: 3217 | H32: -7120 | I32: -9265 | J32: -19087 | K32: =J32*(1+$K$6) -> -19468.74 | L32: =K32*(1+L6) -> -19858.115 | M32: =L32*(1+M6) -> -20255.277 | N32: =M32*(1+N6) -> -20660.383 | O32: =N32*(1+O6) -> -21073.59
C33: EQUITY INVESTMENT ACTIVITY | F33: 4 | G33: -3 | H33: -12 | I33: -101 | J33: -554 | K33: =J33*(1+$K$6) -> -565.08 | L33: =K33*(1+$K$6) -> -576.3816 | M33: =L33*(1+$K$6) -> -587.90923 | N33: =M33*(1+$K$6) -> -599.66742 | O33: =N33*(1+$K$6) -> -611.66076
B36: NET PROFIT | F36: =SUM(F31:F35) -> 33364 | G36: =SUM(G31:G35) -> -2722 | H36: =SUM(H31:H35) -> 30425 | I36: =SUM(I31:I35) -> 59248 | J36: =SUM(J31:J35) -> 77670 | K36: =SUM(K31:K35) -> 82808.02 | L36: =SUM(L31:L35) -> 91812.651 | M36: =SUM(M31:M35) -> 99325.598 | ... O36: =SUM(O31:O35) -> 115946.93
A41: CASHFLOW STATEMENT
C44: All the values are in MILLIONS
F45: =F4 -> 2021 | G45: =G4 -> 2022 | H45: =H4 -> 2023 | I45: =I4 -> 2024 | J45: =J4 -> 2025 | K45: =K4 -> 2026F | L45: =L4 -> 2027F | M45: =M4 -> 2028F | ... O45: =O4 -> 2030F
B48: CASH FROM OPERATING
C49: NET INCOME | F49: =F36 -> 33364 | G49: =G36 -> -2722 | H49: =H36 -> 30425 | I49: =I36 -> 59248 | J49: =J36 -> 77670 | K49: =K36 -> 82808.02 | L49: =L36 -> 91812.651 | M49: =M36 -> 99325.598 | ... O49: =O36 -> 115946.93
C50: TAX PAID | F50: -3688 | G50: -6035 | H50: -11179 | I50: -12308 | J50: -8295
C51: DEPRECIATION | F51: =F22 -> 34433 | G51: =G22 -> 41921 | H51: =H22 -> 48663 | I51: =I22 -> 52795 | J51: =J22 -> 65756 | K51: =H250 -> 32854.718 | L51: =I250 -> 32979.718 | M51: =J250 -> 33098.468 | N51: =K250 -> 33218.781 | O51: =L250 -> 33340.135
C52: CASH FROM AR | F52: -9145 | G52: -8622 | H52: -8348 | I52: =-I201 -> -3198 | J52: =-J201 -> -12278 | K52: =-K201 -> 3304.0488 | L52: =-L201 -> -8153.7829 | M52: =-M201 -> 1200.1412 | N52: =-N201 -> -1962.9113 | O52: =-O201 -> -3203.6737
C53: CASH FROM INVENTORY | F53: -9487 | G53: -2592 | H53: 1149 | I53: =I202 -> 896 | J53: =J202 -> 4111 | K53: =-K202 -> 8444.8126 | L53: =-L202 -> -5677.2356 | M53: =-M202 -> 1879.4638 | N53: =-N202 -> -673.55918 | O53: =-O202 -> -1585.4547
C54: CASH FROM PAYABLES | F54: 3602 | G54: 2945 | H54: 5473 | I54: =I203 -> -9382 | J54: =J203 -> -27546 | K54: =-K203 -> -22308.375 | L54: =-L203 -> 27390.172 | M54: =-M203 -> -10413.245 | N54: =-N203 -> 2331.551 | O54: =-O203 -> 6870.3037
C55: SUB TOTAL | F55: =SUM(F49:F54) -> 49079 | G55: =SUM(G49:G54) -> 24895 | H55: =SUM(H49:H54) -> 66183 | I55: =SUM(I49:I54) -> 88051 | J55: =SUM(J49:J54) -> 99418 | K55: =SUM(K49:K54) -> 105103.22 | L55: =SUM(L49:L54) -> 138351.52 | M55: =SUM(M49:M54) -> 125090.43 | ... O55: =SUM(O49:O54) -> 151368.24
B59: CASH FROM INVESTING
C60: CAPITAL EXPENDITURE | F60: -55396 | G60: -58321 | H60: -48133 | I60: -77658 | J60: -128320 | K60: =-K216 -> -95000 | L60: =-L216 -> -97500 | M60: =-M216 -> -96250 | N60: =-N216 -> -96250 | O60: =-O216 -> -96666.667
C61: SUBTOTAL | F61: -58154 | G61: -37601 | H61: -49833 | I61: -94342 | J61: -142545 | K61: =K60 -> -95000 | L61: =L60 -> -97500 | M61: =M60 -> -96250 | N61: =N60 -> -96250 | O61: =O60 -> -96666.667
B66: CASH FROM FINANCING
C67: CHANGE IN LONG TERM DEBT | F67: 6291 | G67: 15718 | H67: -15879 | I67: -11812 | J67: 9661 | K67: =Input!G67 -> -400 | L67: =Input!H67 -> -450 | M67: =Input!I67 -> -425 | N67: =Input!J67 -> -425 | O67: =Input!K67 -> -433.33333
C69: CHANGE IN COMMON EQUITY | F69: - | G69: -6000 | K69: =Input!G66 -> -2500 | L69: =Input!H66 -> -2500 | M69: =Input!I66 -> -2500 | N69: =Input!J66 -> -2500 | O69: =Input!K66 -> -2500
C70: DIVIDENDS | F70: - | K70: =-K378 -> -8280.802 | L70: =-L378 -> -9181.2651 | M70: =-M378 -> -9932.5598 | N70: =-N378 -> -10714.491 | O70: =-O378 -> -11594.693
C71: SUBTOTAL | F71: =SUM(F67:F70) -> 6291 | G71: =SUM(G67:G70) -> 9718 | H71: =SUM(H67:H70) -> -15879 | I71: =SUM(I67:I70) -> -11812 | J71: =SUM(J67:J70) -> 9661 | K71: =SUM(K67:K70) -> -11180.802 | L71: =SUM(L67:L70) -> -12131.265 | M71: =SUM(M67:M70) -> -12857.56 | ... O71: =SUM(O67:O70) -> -14528.026
B76: CASH BALANCE
C77: BEGINNING YEAR | F77: 42377 | G77: 36477 | H77: 54253 | I77: 73890 | J77: 82312 | K77: =J79 -> 86810 | L77: =K79 -> 85732.422 | M77: =L79 -> 114452.68 | N77: =M79 -> 130435.55 | O77: =N79 -> 160604.83
C78: INCREASE | F78: -5900 | G78: 17776 | H78: 19637 | I78: 8422 | J78: 5000 | K78: =K55+K61+K71 -> -1077.5778 | L78: =L55+L61+L71 -> 28720.258 | M78: =M55+M61+M71 -> 15982.866 | N78: =N55+N61+N71 -> 30169.283 | O78: =O55+O61+O71 -> 40173.545
C79: END OF YEAR | F79: =SUM(F77:F78) -> 36477 | G79: =SUM(G77:G78) -> 54253 | H79: =SUM(H77:H78) -> 73890 | I79: =SUM(I77:I78) -> 82312 | J79: 86810 | K79: =SUM(K77:K78) -> 85732.422 | L79: =SUM(L77:L78) -> 114452.68 | M79: =SUM(M77:M78) -> 130435.55 | N79: =SUM(N77:N78) -> 160604.83 | O79: =SUM(O77:O78) -> 200778.37
A85: BALANCE SHEET
C88: All the values are in MILLIONS
F89: =F45 -> 2021 | G89: =G45 -> 2022 | H89: =H45 -> 2023 | I89: =I45 -> 2024 | J89: =J45 -> 2025 | K89: =K45 -> 2026F | L89: =L45 -> 2027F | M89: =M45 -> 2028F | ... O89: =O45 -> 2030F
B92: ASSETS
B93: CURRENT | C93: CASH | F93: 36220 | G93: 53888 | H93: 73387 | I93: 78779 | J93: 86810 | K93: =K79 -> 85732.422 | L93: =L79 -> 114452.68 | M93: =M79 -> 130435.55 | N93: =N79 -> 160604.83 | O93: =O79 -> 200778.37
C94: ACCOUNTS RECIEVABLE | F94: 32891 | G94: 42360 | H94: 52253 | I94: 55451 | J94: 67729 | K94: =K171 -> 64424.951 | L94: =L171 -> 72578.734 | M94: =M171 -> 71378.593 | N94: =N171 -> 73341.504 | O94: =O171 -> 76545.178
C95: INVENTORIES | F95: 32640 | G95: 34405 | H95: 33318 | I95: 34214 | J95: 38325 | K95: =K173 -> 29880.187 | L95: =L173 -> 35557.423 | M95: =M173 -> 33677.959 | N95: =N173 -> 34351.518 | O95: =O173 -> 35936.973
C96: OTHER CURRENT ASSETS | F96: 59829 | G96: 16138 | H96: 13393 | I96: 22423 | J96: 36219 | K96: =J96 -> 36219 | L96: =K96 -> 36219 | M96: =L96 -> 36219 | N96: =M96 -> 36219 | O96: =N96 -> 36219
C100: TOTAL ASSETS | F100: =SUM(F93:F99) -> 161580 | G100: =SUM(G93:G99) -> 146791 | H100: =SUM(H93:H99) -> 172351 | I100: =SUM(I93:I99) -> 190867 | J100: =SUM(J93:J99) -> 229083 | K100: =SUM(K93:K99) -> 216256.56 | L100: =SUM(L93:L99) -> 258807.84 | M100: =SUM(M93:M99) -> 271711.1 | ... O100: =SUM(O93:O99) -> 349479.53
B101: NONCURRENT
C102: NET PP&E | F102: 160281 | G102: 186715 | H102: 204177 | I102: 252665 | J102: 357025 | K102: =K275 -> 419170.28 | L102: =L275 -> 483690.56 | M102: =M275 -> 546842.1 | N102: =N275 -> 609873.31 | O102: =O275 -> 673199.85
C103: NON Current Assets | F103: 56082 | G103: 66123 | H103: 72513 | I103: 76141 | J103: 86054 | K103: =J103 -> 86054 | L103: =K103 -> 86054 | M103: =L103 -> 86054 | N103: =M103 -> 86054 | O103: =N103 -> 86054
C104: Investments | F104: - | G104: - | H104: - | I104: - | J104: -
C105: Others | F105: 42606 | G105: 63046 | H105: 78813 | I105: 105221 | J105: 145880 | K105: =J105 -> 145880 | L105: =K105 -> 145880 | M105: =L105 -> 145880 | N105: =M105 -> 145880 | O105: =N105 -> 145880
C109: TOTAL ASSETS | F109: =SUM(F100:F108) -> 420549 | G109: =SUM(G100:G108) -> 462675 | H109: =SUM(H100:H108) -> 527854 | I109: =SUM(I100:I108) -> 624894 | J109: =SUM(J100:J108) -> 818042 | K109: =SUM(K100:K108) -> 867360.84 | L109: =SUM(L100:L108) -> 974432.4 | M109: =SUM(M100:M108) -> 1050487.2 | ... O109: =SUM(O100:O108) -> 1254613.4
B111: LIABILITIES
B112: CURRENT
C113: ACCOUNTS PAYABLE | F113: 78664 | G113: 79600 | H113: 84981 | I113: 94363 | J113: 121909 | K113: =K175 -> 99600.625 | L113: =L175 -> 126990.8 | M113: =M175 -> 116577.55 | N113: =N175 -> 118909.1 | O113: =O175 -> 125779.41
C114: OTHER CURRENT LIABILITIES | F114: 63602 | G114: 75793 | H114: 79936 | I114: 85068 | J114: 96096 | K114: =J114 -> 96096 | L114: =K114 -> 96096 | M114: =L114 -> 96096 | N114: =M114 -> 96096 | O114: =N114 -> 96096
C118: TOTAL CURRENT LIABILITIES | F118: =SUM(F113:F117) -> 142266 | G118: =SUM(G113:G117) -> 155393 | H118: =SUM(H113:H117) -> 164917 | I118: =SUM(I113:I117) -> 179431 | J118: =SUM(J113:J117) -> 218005 | K118: =SUM(K113:K117) -> 195696.62 | L118: =SUM(L113:L117) -> 223086.8 | M118: =SUM(M113:M117) -> 212673.55 | ... O118: =SUM(O113:O117) -> 221875.41
B119: NON CURRENT LIABILITIES
C120: LONG TERM DEBT | F120: 48744 | G120: 67150 | H120: 58314 | I120: 52623 | J120: 65648 | K120: =K313 -> 65248 | L120: =L313 -> 64798 | M120: =M313 -> 64373 | N120: =N313 -> 63948 | O120: =O313 -> 63514.667
C121: Other Non-Current Liabilities | F121: 91294 | G121: 94089 | H121: 102748 | I121: 106870 | J121: 123324 | K121: =J121 -> 123324 | L121: =K121 -> 123324 | M121: =L121 -> 123324 | N121: =M121 -> 123324 | O121: =N121 -> 123324
C122: TOTAL LIABILITIES | F122: =SUM(F118:F121) -> 282304 | G122: =SUM(G118:G121) -> 316632 | H122: =SUM(H118:H121) -> 325979 | I122: =SUM(I118:I121) -> 338924 | J122: =SUM(J118:J121) -> 406977 | K122: =SUM(K118:K121) -> 384268.62 | L122: =SUM(L118:L121) -> 411208.8 | M122: =SUM(M118:M121) -> 400370.55 | ... O122: =SUM(O118:O121) -> 408714.07
B125: EQUITY
C126: COMMON EQUITY | F126: 52330 | G126: 62850 | H126: 88257 | I126: 113104 | J126: 160529 | K126: =K373 -> 158029 | L126: =L373 -> 155529 | M126: =M373 -> 153029 | N126: =N373 -> 150529 | O126: =O373 -> 148029
C127: RETAINED EARNINGS | F127: 85915 | G127: 83193 | H127: 113618 | I127: 172866 | J127: 250536 | K127: =K388 -> 325063.22 | L127: =L388 -> 407694.6 | M127: =M388 -> 497087.64 | N127: =N388 -> 593518.06 | O127: =O388 -> 697870.3
C128: TOTAL SHAREHOLDERS EQUITY | F128: =SUM(F126:F127) -> 138245 | G128: =SUM(G126:G127) -> 146043 | H128: =SUM(H126:H127) -> 201875 | I128: =SUM(I126:I127) -> 285970 | J128: =SUM(J126:J127) -> 411065 | K128: =SUM(K126:K127) -> 483092.22 | L128: =SUM(L126:L127) -> 563223.6 | M128: =SUM(M126:M127) -> 650116.64 | ... O128: =SUM(O126:O127) -> 845899.3
B129: %Change in equity
C131: TOTAL LIABILITIES AND EQUITY | F131: =SUM(,F128,F122) -> 420549 | G131: =SUM(,G128,G122) -> 462675 | H131: =SUM(,H128,H122) -> 527854 | I131: =SUM(,I128,I122) -> 624894 | J131: =SUM(,J128,J122) -> 818042 | K131: =SUM(,K128,K122) -> 867360.84 | L131: =SUM(,L128,L122) -> 974432.4 | M131: =SUM(,M128,M122) -> 1050487.2 | ... O131: =SUM(,O128,O122) -> 1254613.4
B133: SIGNALS | F133: =IF(ABS(F109-F131)=0,"Balanced",F131-F109) -> Balanced | G133: =IF(ABS(G109-G131)=0,"Balanced",G131-G109) -> Balanced | H133: =IF(ABS(H109-H131)=0,"Balanced",H131-H109) -> Balanced | I133: =IF(ABS(I109-I131)=0,"Balanced",I131-I109) -> Balanced | J133: =IF(ABS(J109-J131)=0,"Balanced",J131-J109) -> Balanced | K133: =IF(ABS(K109-K131)=0,"Balanced",K131-K109) -> Balanced | L133: =IF(ABS(L109-L131)=0,"Balanced",L131-L109) -> Balanced | M133: =IF(ABS(M109-M131)=0,"Balanced",M131-M109) -> Balanced | ... O133: =IF(ABS(O109-O131)=0,"Balanced",O131-O109) -> -2.3283064e-10
A135: REVENUE SCHEDULE
C138: All the values are in MILLIONS
F140: =F89 -> 2021 | G140: =G89 -> 2022 | H140: =H89 -> 2023 | I140: =I89 -> 2024 | J140: =J89 -> 2025 | K140: =K89 -> 2026F | L140: =L89 -> 2027F | M140: =M89 -> 2028F | ... O140: =O89 -> 2030F
B142: REVENUE | F142: =F9 -> 469822 | G142: =G9 -> 513983 | H142: =H9 -> 574785 | I142: =I9 -> 637959 | J142: =J9 -> 716924 | K142: =K160 -> 734847.1 | L142: =L160 -> 756892.51 | M142: =M160 -> 777707.06 | N142: =N160 -> 799094 | O142: =O160 -> 821735
B143: OPERATIONS
B145: REVENUE GROWTH | G145: =G142/F142-1 -> 0.093995173 | H145: =H142/G142-1 -> 0.11829574 | I145: =I142/H142-1 -> 0.10990892 | J145: =J142/I142-1 -> 0.12377755 | K145: =Input!G9 -> 0.025 | L145: =Input!H9 -> 0.03 | M145: =Input!I9 -> 0.0275 | N145: =Input!J9 -> 0.0275 | O145: =Input!K9 -> 0.028333333
C149: PRODUCT SALES | G149: =H149/(1+G145) -> 233901.4 | H149: 255887 | I149: 272311 | J149: 296266 | K149: =J149*(1+K145) -> 303672.65 | L149: =K149*(1+L145) -> 312782.83 | M149: =L149*(1+M145) -> 321384.36 | N149: =M149*(1+N145) -> 330222.43 | O149: =N149*(1+O145) -> 339578.73
C151: SERVICE SALES | G151: =H151/(1+G145) -> 291498.54 | H151: 318898 | I151: 365648 | J151: 420658 | K151: =J151*(1+K145) -> 431174.45 | L151: =K151*(1+L145) -> 444109.68 | M151: =L151*(1+M145) -> 456322.7 | N151: =M151*(1+N145) -> 468871.57 | O151: =N151*(1+O145) -> 482156.27
C153: PRODUCT SALES GROWTH | H153: =H149/G149-1 -> 0.093995173 | I153: =I149/H149-1 -> 0.064184581 | J153: =J149/I149-1 -> 0.08796927 | K153: =K149/J149-1 -> 0.025 | L153: =L149/K149-1 -> 0.03 | M153: =M149/L149-1 -> 0.0275 | N153: =N149/M149-1 -> 0.0275 | O153: =O149/N149-1 -> 0.028333333
C155: SERVICE SALES GROWTH | H155: =H151/G151-1 -> 0.093995173 | I155: =I151/H151-1 -> 0.1465986 | J155: =J151/I151-1 -> 0.15044524 | K155: =K151/J151-1 -> 0.025 | L155: =L151/K151-1 -> 0.03 | M155: =M151/L151-1 -> 0.0275 | N155: =N151/M151-1 -> 0.0275 | O155: =O151/N151-1 -> 0.028333333
B158: PRODUCT SALES | I158: =I149 -> 272311 | J158: =J149 -> 296266 | K158: =K149 -> 303672.65 | L158: =L149 -> 312782.83 | M158: =M149 -> 321384.36 | N158: =N149 -> 330222.43 | O158: =O149 -> 339578.73
B159: SERVICE SALES | I159: =I151 -> 365648 | J159: =J151 -> 420658 | K159: =K151 -> 431174.45 | L159: =L151 -> 444109.68 | M159: =M151 -> 456322.7 | N159: =N151 -> 468871.57 | O159: =O151 -> 482156.27
B160: TOTAL REVENUE | I160: =SUM(I158:I159) -> 637959 | J160: =SUM(J158:J159) -> 716924 | K160: =SUM(K158:K159) -> 734847.1 | L160: =SUM(L158:L159) -> 756892.51 | M160: =SUM(M158:M159) -> 777707.06 | N160: =SUM(N158:N159) -> 799094 | O160: =SUM(O158:O159) -> 821735
A165: WORKING CAPITAL SCHEDULE
C168: All the values are in MILLIONS
F170: =F140 -> 2021 | G170: =G140 -> 2022 | H170: =H140 -> 2023 | I170: =I140 -> 2024 | J170: =J140 -> 2025 | K170: =K140 -> 2026F | L170: =L140 -> 2027F | M170: =M140 -> 2028F | ... O170: =O140 -> 2030F
B171: AR | F171: =F94 -> 32891 | G171: =G94 -> 42360 | H171: =H94 -> 52253 | I171: =I94 -> 55451 | J171: =J94 -> 67729 | K171: =K193 -> 64424.951 | L171: =L193 -> 72578.734 | M171: =M193 -> 71378.593 | N171: =N193 -> 73341.504 | O171: =O193 -> 76545.178
B173: INVENTORY | F173: =F95 -> 32640 | G173: =G95 -> 34405 | H173: =H95 -> 33318 | I173: =I95 -> 34214 | J173: =J95 -> 38325 | K173: =K194 -> 29880.187 | L173: =L194 -> 35557.423 | M173: =M194 -> 33677.959 | N173: =N194 -> 34351.518 | O173: =O194 -> 35936.973
B175: AP | F175: =F113 -> 78664 | G175: =G113 -> 79600 | H175: =H113 -> 84981 | I175: =I113 -> 94363 | J175: =J113 -> 121909 | K175: =K195 -> 99600.625 | L175: =L195 -> 126990.8 | M175: =M195 -> 116577.55 | N175: =N195 -> 118909.1 | O175: =O195 -> 125779.41
F176: 0
B178: DAYS IN PERIOD | F178: 365 | G178: 365 | H178: 365 | I178: 365 | J178: 365 | K178: 365 | L178: 365 | M178: 365 | N178: 365 | O178: 365
B179: REVENUE | F179: =F142 -> 469822 | G179: =G142 -> 513983 | H179: =H142 -> 574785 | I179: =I142 -> 637959 | J179: =J142 -> 716924 | K179: =K142 -> 734847.1 | L179: =L142 -> 756892.51 | M179: =M142 -> 777707.06 | ... O179: =O142 -> 821735
...
